get_proxy.py
get_proxy-1.0.4.dist-info/DESCRIPTION.rst
get_proxy-1.0.4.dist-info/METADATA
get_proxy-1.0.4.dist-info/RECORD
get_proxy-1.0.4.dist-info/WHEEL
get_proxy-1.0.4.dist-info/metadata.json
get_proxy-1.0.4.dist-info/top_level.txt
