Metadata-Version: 2.0
Name: get-proxy
Version: 1.0.4
Summary: get proxies
Home-page: UNKNOWN
Author: Lewie Luo
Author-email: luoyang941122@163.com
License: UNKNOWN
Platform: UNKNOWN
